Metadata-Version: 1.1
Name: brat-reader
Version: 0.0.0
Summary: Work with the PARC dataset in Python
Home-page: https://github.com/enewe101/brat-reader
Author: Edward Newell
Author-email: edward.newell@gmail.com
License: MIT
Keywords: BRAT annotation NLP natrual language processing computational linguistics
Platform: UNKNOWN
Classifier: Development Status :: 3 - Alpha
Classifier: Intended Audience :: Developers
Classifier: Topic :: Software Development :: Build Tools
Classifier: License :: OSI Approved :: MIT License
Classifier: Programming Language :: Python :: 2.7
